financeager/__init__.py
financeager/cli.py
financeager/clients.py
financeager/config.py
financeager/entries.py
financeager/exceptions.py
financeager/listing.py
financeager/localserver.py
financeager/plugin.py
financeager/pocket.py
financeager/rich.py
financeager/server.py
financeager-1.5.1.dist-info/licenses/LICENSE.md
financeager-1.5.1.dist-info/METADATA
financeager-1.5.1.dist-info/WHEEL
financeager-1.5.1.dist-info/entry_points.txt
financeager-1.5.1.dist-info/top_level.txt
financeager-1.5.1.dist-info/RECORD
