Metadata-Version: 2.4
Name: financeager
Version: 1.5.1
Summary: command line tool for organizing finances
Author-email: Philipp Metzner <beth.aleph@yahoo.de>
License: GPLv3
Project-URL: Bug Tracker, https://github.com/pylipp/financeager/issues
Project-URL: Documentation, https://github.com/pylipp/financeager
Project-URL: Homepage, https://github.com/pylipp/financeager
Project-URL: Source Code, https://github.com/pylipp/financeager
Keywords: commandline,finances
Classifier: Development Status :: 3 - Alpha
Classifier: Environment :: Console
Classifier: Intended Audience :: End Users/Desktop
Classifier: Intended Audience :: Other Audience
Classifier: License :: OSI Approved :: GNU General Public License v3 (GPLv3)
Classifier: Operating System :: Unix
Classifier: Programming Language :: Python :: 3.10
Classifier: Programming Language :: Python :: 3.11
Classifier: Programming Language :: Python :: 3.12
Classifier: Programming Language :: Python :: 3.13
Classifier: Programming Language :: Python :: 3.14
Classifier: Topic :: Office/Business :: Financial
Classifier: Topic :: Database
Classifier: Topic :: Utilities
Requires-Python: >=3.10
License-File: LICENSE.md
Requires-Dist: platformdirs==4.5.1
Requires-Dist: argcomplete==3.6.3
Requires-Dist: marshmallow==4.1.2
Requires-Dist: python-dateutil==2.9.0.post0
Requires-Dist: rich==14.2.0
Requires-Dist: tinydb==4.8.2
Provides-Extra: develop
Requires-Dist: black==25.12.0; extra == "develop"
Requires-Dist: coverage==7.13.1; extra == "develop"
Requires-Dist: flake8==7.3.0; extra == "develop"
Requires-Dist: flake8-pyproject==1.2.4; extra == "develop"
Requires-Dist: gitlint-core==0.19.1; extra == "develop"
Requires-Dist: isort==7.0.0; extra == "develop"
Requires-Dist: pre-commit==4.5.1; extra == "develop"
Provides-Extra: packaging
Requires-Dist: build; extra == "packaging"
Dynamic: license-file
